{"name":"shoes","uid":"@MAT--9b62e0-7ebeb-18cb370-a0","diffuse":[1,1,1],"shader_name":"global","blend_mode":"normal","uvs_matrix":[1,0,0,0,1,0,0,0,1],"textures":{"color":{"texture":"gerard/textures/classicshoes_texture_diffuse.png"},"normal":{"texture":"gerard/textures/classicshoes_texture_normals.png"}},"color":[1,1,1],"opacity":1,"specular_factor":0.10000000149011612,"specular_gloss":10,"ambient":[1,1,1],"emissive":[0,0,0],"backlight_factor":0,"specular_ontop":false,"reflection_factor":0,"reflection_fresnel":1,"reflection_additive":false,"reflection_specular":false,"velvet":[0.5,0.5,0.5],"velvet_exp":0,"velvet_additive":false,"normalmap_factor":1,"displacementmap_factor":0.1,"bumpmap_factor":1,"use_scene_ambient":true,"extra_surface_shader_code":"","extra_uniforms":{},"normalmap_tangent":true,"object_type":"StandardMaterial","preview":{},"id":null,"filename":"shoes.json","fullpath":"gerard/materials/shoes.json","detail_factor":0,"detail_scale":[10,10],"extra_factor":0,"extra_color":[0,0,0],"material_class":"StandardMaterial"}